<Collection>
  <amount_string><skip>THIS</skip> <skip>AGREEMENT</skip> <skip>made</skip> <skip>and</skip> <skip>entered</skip> <skip>into</skip> <skip>this</skip> <skip>____lst_</skip> <skip>day</skip> <skip>of</skip> <skip>July</skip> <skip>2009</skip> <skip>by</skip> <skip>and</skip> <skip>between</skip> <skip>the</skip> <skip>City</skip> <skip>of</skip> <skip>New</skip> <skip>Orleans</skip> <skip>herein</skip> <skip>represented</skip> <skip>by</skip> <skip>C</skip> <skip>Ray</skip> <skip>Nagin</skip> <skip>Mayor</skip> <skip>City</skip> <skip>and</skip> <skip>Rhonda</skip> <skip>Cook</skip> <skip>herein</skip> <skip>represented</skip> <skip>by</skip> <skip>Contractor</skip> <skip>witnesses</skip> <skip>that</skip> <skip>WHEREAS</skip> <skip>the</skip> <skip>City</skip> <skip>desires</skip> <skip>to</skip> <skip>engage</skip> <skip>the</skip> <skip>Contractor</skip> <skip>to</skip> <skip>render</skip> <skip>311</skip> <skip>Contact</skip> <skip>Center</skip> <skip>consulting</skip> <skip>and</skip> <skip>project</skip> <skip>management</skip> <skip>services</skip> <skip>representing</skip> <skip>the</skip> <skip>City</skip> <skip>in</skip> <skip>the</skip> <skip>311</skip> <skip>Contact</skip> <skip>Center</skip> <skip>and</skip> <skip>WHEREAS</skip> <skip>Contractor</skip> <skip>whose</skip> <skip>office</skip> <skip>is</skip> <skip>located</skip> <skip>at</skip> <skip>3435</skip> <skip>Ocala</skip> <skip>Ave</skip> <skip>Baton</skip> <skip>Rouge</skip> <skip>La</skip> <skip>70814</skip> <skip>is</skip> <skip>qualified</skip> <skip>and</skip> <skip>willing</skip> <skip>to</skip> <skip>perform</skip> <skip>such</skip> <skip>services</skip> <skip>and</skip> <skip>both</skip> <skip>the</skip> <skip>City</skip> <skip>and</skip> <skip>the</skip> <skip>Contractor</skip> <skip>desire</skip> <skip>hereby</skip> <skip>to</skip> <skip>detail</skip> <skip>their</skip> <skip>related</skip> <skip>agreement</skip> <skip>NOW</skip> <skip>THEREFORE</skip> <skip>the</skip> <skip>City</skip> <skip>of</skip> <skip>New</skip> <skip>Orleans</skip> <skip>and</skip> <skip>the</skip> <skip>Contractor</skip> <skip>for</skip> <skip>the</skip> <skip>consideration</skip> <skip>and</skip> <skip>under</skip> <skip>the</skip> <skip>conditions</skip> <skip>set</skip> <skip>forth</skip> <skip>agree</skip> <skip>as</skip> <skip>follows</skip> <skip>1</skip> <skip>CONTRACTED</skip> <skip>SERVICES</skip> <skip>311</skip> <skip>Contact</skip> <skip>Center</skip> <skip>consulting</skip> <skip>and</skip> <skip>project</skip> <skip>management</skip> <skip>services</skip> <skip>representing</skip> <skip>the</skip> <skip>City</skip> <skip>in</skip> <skip>311</skip> <skip>Contact</skip> <skip>Center</skip> <skip>2</skip> <skip>FEES</skip> <skip>The</skip> <skip>City</skip> <skip>will</skip> <skip>pay</skip> <skip>the</skip> <skip>Contractor</skip> <skip>to</skip> <skip>perform</skip> <skip>the</skip> <skip>contracted</skip> <skip>services</skip> <skip>according</skip> <skip>to</skip> <skip>the</skip> <other_amount_padding>following</other_amount_padding> <other_amount_padding>fee</other_amount_padding> <other_amount_padding>schedule</other_amount_padding> <skip>311</skip> <other_amount_padding>Contact</other_amount_padding> <other_amount_padding>Consulting</other_amount_padding> <other_amount_padding>Project</other_amount_padding> <other_amount_padding>Managing</other_amount_padding> <other_amount>$1,459.00</other_amount> <other_amount_padding>Weekly</other_amount_padding> <skip>The</skip> <skip>City</skip> <skip>will</skip> <skip>also</skip> <skip>reimburse</skip> <skip>the</skip> <skip>contractor</skip> <skip>for</skip> <skip>approved</skip> <skip>out</skip> <skip>of</skip> <skip>pocket</skip> <skip>costs</skip> <skip>including</skip> <skip>costs</skip> <skip>for</skip> <skip>photocopying</skip> <skip>messenger</skip> <skip>and</skip> <skip>delivery</skip> <skip>services</skip> <skip>computerized</skip> <skip>research</skip> <skip>travel</skip> <skip>long</skip> <skip>distance</skip> <skip>telephone</skip> <skip>and</skip> <skip>telecopy</skip> <skip>and</skip> <skip>search</skip> <skip>and</skip> <skip>filing</skip> <skip>fees</skip> <contract_amount_padding>The</contract_amount_padding> <contract_amount_padding>maximum</contract_amount_padding> <contract_amount_padding>sum</contract_amount_padding> <contract_amount_padding>payable</contract_amount_padding> <contract_amount_padding>under</contract_amount_padding> <contract_amount_padding>this</contract_amount_padding> <contract_amount_padding>Agreement</contract_amount_padding> <contract_amount_padding>is</contract_amount_padding> <contract_amount>$15,000.00</contract_amount> <skip>The</skip> <skip>Contractor</skip> <skip>shall</skip> <skip>submit</skip> <skip>to</skip> <skip>the</skip> <skip>City</skip> <skip>a</skip> <skip>detailed</skip> <skip>monthly</skip> <skip>invoice</skip> <skip>for</skip> <skip>payment</skip> <skip>for</skip> <skip>services</skip> <skip>provided</skip> <skip>3</skip> <skip>TERM</skip> <skip>The</skip> <skip>term</skip> <skip>of</skip> <skip>this</skip> <skip>Agreement</skip> <skip>is</skip> <skip>July</skip> <skip>1</skip> <skip>2009</skip> <skip>to</skip> <skip>September</skip> <skip>30</skip> <skip>2009</skip> <skip>4</skip> <skip>FURTHER</skip> <skip>PROVISIONS</skip> <skip>a</skip> <skip>The</skip> <skip>City</skip> <skip>and</skip> <skip>the</skip> <skip>Contractor</skip> <skip>bind</skip> <skip>themselves</skip> <skip>under</skip> <skip>the</skip> <skip>Additional</skip> <skip>Terms</skip> <skip>and</skip> <skip>Conditions</skip> <skip>attached</skip> <skip>hereto</skip> <skip>5</skip> <skip>AMENDMENT</skip> <skip>This</skip> <skip>agreement</skip> <skip>is</skip> <skip>not</skip> <skip>modified</skip> <skip>except</skip> <skip>by</skip> <skip>written</skip> <skip>amendment</skip> <skip>executed</skip> <skip>by</skip> <skip>the</skip> <skip>parties</skip> <skip>hereto</skip> <skip>IN</skip> <skip>WITNESS</skip> <skip>WHEREOF</skip> <skip>the</skip> <skip>parties</skip> <skip>hereto</skip> <skip>have</skip> <skip>made</skip> <skip>and</skip> <skip>executed</skip> <skip>this</skip> <skip>Agreement</skip> <skip>effective</skip> <skip>the</skip> <skip>day</skip> <skip>and</skip> <skip>year</skip> <skip>first</skip> <skip>above</skip> <skip>written</skip> <skip>CITY</skip> <skip>OF</skip> <skip>NEW</skip> <skip>ORLEANS</skip> <skip>By</skip> <skip>C</skip> <skip>RAY</skip> <skip>N</skip> <skip>Th</skip> <skip>MAYOR</skip> <skip>YK</skip> <skip>B</skip> <skip>Rbonda</skip> <skip>Cook</skip> <skip>Tax</skip> <skip>ID</skip> <skip>No</skip> <skip>TAX</skip> <skip>IDI</skip> <skip>LEGALItY</skip> <skip>PRQVD</skip> <skip>New</skip> <skip>OrleaJlF</skip> <skip>ATTACHMENT</skip> <skip>ADDITIONAL</skip> <skip>TERMS</skip> <skip>AND</skip> <skip>CONDITIONS</skip> <skip>PROFESSIONAL</skip> <skip>SERVICES</skip> <skip>AGREEMENT</skip> <skip>BETWEEN</skip> <skip>THE</skip> <skip>CITY</skip> <skip>OF</skip> <skip>NEW</skip> <skip>ORLEANS</skip> <skip>City</skip> <skip>AND</skip> <skip>FIRMI</skip> <skip>Contractor</skip> <skip>EQUAL</skip> <skip>EMPLOYMENT</skip> <skip>OPPORTUNITY</skip> <skip>In</skip> <skip>all</skip> <skip>hiring</skip> <skip>or</skip> <skip>employment</skip> <skip>made</skip> <skip>possible</skip> <skip>by</skip> <skip>or</skip> <skip>1</skip> <skip>resulting</skip> <skip>from</skip> <skip>this</skip> <skip>contract</skip> <skip>there</skip> <skip>1</skip> <skip>will</skip> <skip>not</skip> <skip>be</skip> <skip>any</skip> <skip>discrimination</skip> <skip>against</skip> <skip>any</skip> <skip>employee</skip> <skip>or</skip> <skip>applicant</skip> <skip>for</skip> <skip>employment</skip> <skip>because</skip> <skip>of</skip> <skip>race</skip> <skip>color</skip> <skip>religion</skip> <skip>gender</skip> <skip>age</skip> <skip>physical</skip> <skip>or</skip> <skip>mental</skip> <skip>disability</skip> <skip>national</skip> <skip>origin</skip> <skip>sexual</skip> <skip>orientation</skip> <skip>creed</skip> <skip>culture</skip> <skip>or</skip> <skip>ancestry</skip> <skip>and</skip> <skip>2</skip> <skip>where</skip> <skip>applicable</skip> <skip>affirmative</skip> <skip>action</skip> <skip>will</skip> <skip>be</skip> <skip>taken</skip> <skip>to</skip> <skip>ensure</skip> <skip>that</skip> <skip>the</skip> <skip>Contractors</skip> <skip>employees</skip> <skip>are</skip> <skip>treated</skip> <skip>during</skip> <skip>employment</skip> <skip>without</skip> <skip>regard</skip> <skip>to</skip> <skip>their</skip> <skip>race</skip> <skip>color</skip> <skip>religion</skip> <skip>gender</skip> <skip>age</skip> <skip>physical</skip> <skip>or</skip> <skip>mental</skip> <skip>disability</skip> <skip>national</skip> <skip>origin</skip> <skip>sexual</skip> <skip>orientation</skip> <skip>creed</skip> <skip>culture</skip> <skip>or</skip> <skip>ancestry</skip> <skip>This</skip> <skip>requirement</skip> <skip>shall</skip> <skip>apply</skip> <skip>to</skip> <skip>but</skip> <skip>not</skip> <skip>be</skip> <skip>limited</skip> <skip>to</skip> <skip>the</skip> <skip>following</skip> <skip>employment</skip> <skip>upgrading</skip> <skip>demotion</skip> <skip>or</skip> <skip>transfer</skip> <skip>recruitment</skip> <skip>or</skip> <skip>recruitment</skip> <skip>advertising</skip> <skip>layoff</skip> <skip>or</skip> <skip>termination</skip> <skip>rates</skip> <skip>of</skip> <skip>pay</skip> <skip>or</skip> <skip>other</skip> <skip>forms</skip> <skip>of</skip> <skip>compensation</skip> <skip>and</skip> <skip>selection</skip> <skip>for</skip> <skip>training</skip> <skip>including</skip> <skip>apprenticeship</skip> <skip>All</skip> <skip>solicitations</skip> <skip>or</skip> <skip>advertisements</skip> <skip>for</skip> <skip>employees</skip> <skip>shall</skip> <skip>state</skip> <skip>that</skip> <skip>all</skip> <skip>qualified</skip> <skip>applicants</skip> <skip>will</skip> <skip>receive</skip> <skip>consideration</skip> <skip>for</skip> <skip>employment</skip> <skip>without</skip> <skip>regard</skip> <skip>to</skip> <skip>race</skip> <skip>color</skip> <skip>religion</skip> <skip>gender</skip> <skip>age</skip> <skip>physical</skip> <skip>or</skip> <skip>mental</skip> <skip>disability</skip> <skip>national</skip> <skip>origin</skip> <skip>sexual</skip> <skip>orientation</skip> <skip>creed</skip> <skip>culture</skip> <skip>or</skip> <skip>ancestry</skip> <skip>ASSIGNABILITY</skip> <skip>The</skip> <skip>Contractor</skip> <skip>shall</skip> <skip>not</skip> <skip>assign</skip> <skip>any</skip> <skip>interest</skip> <skip>in</skip> <skip>this</skip> <skip>agreement</skip> <skip>and</skip> <skip>shall</skip> <skip>not</skip> <skip>2</skip> <skip>transfer</skip> <skip>any</skip> <skip>interest</skip> <skip>in</skip> <skip>the</skip> <skip>same</skip> <skip>without</skip> <skip>prior</skip> <skip>written</skip> <skip>consent</skip> <skip>of</skip> <skip>the</skip> <skip>City</skip> <skip>of</skip> <skip>New</skip> <skip>Orleans</skip> <skip>CONFLICT</skip> <skip>OF</skip> <skip>INTEREST</skip> <skip>In</skip> <skip>the</skip> <skip>interest</skip> <skip>of</skip> <skip>ensuring</skip> <skip>that</skip> <skip>efforts</skip> <skip>of</skip> <skip>the</skip> <skip>Contractor</skip> <skip>do</skip> <skip>not</skip> <skip>conflict</skip> <skip>3</skip> <skip>with</skip> <skip>the</skip> <skip>interests</skip> <skip>of</skip> <skip>the</skip> <skip>City</skip> <skip>and</skip> <skip>in</skip> <skip>recognition</skip> <skip>of</skip> <skip>the</skip> <skip>Contractor</skip> <skip>s</skip> <skip>responsibility</skip> <skip>to</skip> <skip>the</skip> <skip>City</skip> <skip>the</skip> <skip>Contractor</skip> <skip>agrees</skip> <skip>to</skip> <skip>decline</skip> <skip>any</skip> <skip>offer</skip> <skip>of</skip> <skip>employment</skip> <skip>if</skip> <skip>its</skip> <skip>independent</skip> <skip>work</skip> <skip>on</skip> <skip>behalf</skip> <skip>of</skip> <skip>the</skip> <skip>City</skip> <skip>is</skip> <skip>likely</skip> <skip>to</skip> <skip>be</skip> <skip>adversely</skip> <skip>affected</skip> <skip>by</skip> <skip>the</skip> <skip>acceptance</skip> <skip>of</skip> <skip>such</skip> <skip>employment</skip> <skip>The</skip> <skip>initial</skip> <skip>determination</skip> <skip>of</skip> <skip>such</skip> <skip>a</skip> <skip>possibility</skip> <skip>rests</skip> <skip>with</skip> <skip>the</skip> <skip>Contractor</skip> <skip>It</skip> <skip>is</skip> <skip>incumbent</skip> <skip>upon</skip> <skip>the</skip> <skip>Contractor</skip> <skip>to</skip> <skip>notify</skip> <skip>the</skip> <skip>City</skip> <skip>and</skip> <skip>provide</skip> <skip>full</skip> <skip>disclosure</skip> <skip>of</skip> <skip>the</skip> <skip>possible</skip> <skip>effects</skip> <skip>of</skip> <skip>such</skip> <skip>employment</skip> <skip>on</skip> <skip>the</skip> <skip>Contractor</skip> <skip>s</skip> <skip>independent</skip> <skip>work</skip> <skip>in</skip> <skip>behalf</skip> <skip>of</skip> <skip>the</skip> <skip>City</skip> <skip>Final</skip> <skip>decision</skip> <skip>on</skip> <skip>any</skip> <skip>disputed</skip> <skip>offers</skip> <skip>of</skip> <skip>other</skip> <skip>employment</skip> <skip>for</skip> <skip>the</skip> <skip>Contractor</skip> <skip>shall</skip> <skip>rest</skip> <skip>with</skip> <skip>the</skip> <skip>City</skip> <skip>INDEMNIFICATION</skip> <skip>The</skip> <skip>Contractor</skip> <skip>shall</skip> <skip>indenmify</skip> <skip>and</skip> <skip>save</skip> <skip>the</skip> <skip>City</skip> <skip>harmless</skip> <skip>against</skip> <skip>any</skip> <skip>and</skip> <skip>4</skip> <skip>all</skip> <skip>claims</skip> <skip>demands</skip> <skip>suits</skip> <skip>judgments</skip> <skip>of</skip> <skip>sums</skip> <skip>of</skip> <skip>money</skip> <skip>to</skip> <skip>any</skip> <skip>party</skip> <skip>accruing</skip> <skip>against</skip> <skip>the</skip> <skip>City</skip> <skip>for</skip> <skip>loss</skip> <skip>of</skip> <skip>life</skip> <skip>or</skip> <skip>injury</skip> <skip>or</skip> <skip>damage</skip> <skip>to</skip> <skip>persons</skip> <skip>or</skip> <skip>property</skip> <skip>growing</skip> <skip>out</skip> <skip>of</skip> <skip>resulting</skip> <skip>from</skip> <skip>or</skip> <skip>by</skip> <skip>reason</skip> <skip>of</skip> <skip>any</skip> <skip>act</skip> <skip>or</skip> <skip>omission</skip> <skip>or</skip> <skip>the</skip> <skip>operation</skip> <skip>of</skip> <skip>the</skip> <skip>Contractor</skip> <skip>its</skip> <skip>agents</skip> <skip>servants</skip> <skip>or</skip> <skip>employees</skip> <skip>while</skip> <skip>engaged</skip> <skip>in</skip> <skip>or</skip> <skip>about</skip> <skip>or</skip> <skip>in</skip> <skip>connection</skip> <skip>with</skip> <skip>the</skip> <skip>discharge</skip> <skip>or</skip> <skip>performance</skip> <skip>of</skip> <skip>the</skip> <skip>services</skip> <skip>to</skip> <skip>be</skip> <skip>done</skip> <skip>or</skip> <skip>performed</skip> <skip>by</skip> <skip>the</skip> <skip>Contractor</skip> <skip>hereunder</skip> <skip>and</skip> <skip>shall</skip> <skip>also</skip> <skip>hold</skip> <skip>the</skip> <skip>City</skip> <skip>harmless</skip> <skip>from</skip> <skip>any</skip> <skip>and</skip> <skip>all</skip> <skip>claims</skip> <skip>and</skip> <skip>or</skip> <skip>liens</skip> <skip>for</skip> <skip>labor</skip> <skip>services</skip> <skip>or</skip> <skip>materials</skip> <skip>furnished</skip> <skip>to</skip> <skip>the</skip> <skip>Contractor</skip> <skip>in</skip> <skip>connection</skip> <skip>with</skip> <skip>the</skip> <skip>performance</skip> <skip>of</skip> <skip>its</skip> <skip>obligation</skip> <skip>under</skip> <skip>this</skip> <skip>Agreement</skip> <skip>ACKNOWLEDGMENT</skip> <skip>OF</skip> <skip>EXCLUSION</skip> <skip>OF</skip> <skip>WORKER</skip> <skip>S</skip> <skip>COMPENSATION</skip> <skip>COVERAGE</skip> <skip>5</skip> <skip>Contractor</skip> <skip>herein</skip> <skip>expressly</skip> <skip>agrees</skip> <skip>and</skip> <skip>acknowledges</skip> <skip>that</skip> <skip>it</skip> <skip>is</skip> <skip>an</skip> <skip>independent</skip> <skip>contractor</skip> <skip>as</skip> <skip>defined</skip> <skip>in</skip> <skip>R</skip> <skip>S</skip> <skip>23</skip> <skip>1021</skip> <skip>6</skip> <skip>and</skip> <skip>as</skip> <skip>such</skip> <skip>it</skip> <skip>is</skip> <skip>expressly</skip> <skip>agreed</skip> <skip>and</skip> <skip>understood</skip> <skip>between</skip> <skip>the</skip> <skip>parties</skip> <skip>hereto</skip> <skip>in</skip> <skip>entering</skip> <skip>into</skip> <skip>this</skip> <skip>services</skip> <skip>agreement</skip> <skip>that</skip> <skip>the</skip> <skip>City</skip> <skip>of</skip> <skip>New</skip> <skip>Orleans</skip> <skip>shall</skip> <skip>not</skip> <skip>be</skip> <skip>liable</skip> <skip>to</skip> <skip>the</skip> <skip>Contractor</skip> <skip>for</skip> <skip>any</skip> <skip>benefits</skip> <skip>or</skip> <skip>coverage</skip> <skip>as</skip> <skip>provided</skip> <skip>by</skip> <skip>the</skip> <skip>Workmen</skip> <skip>s</skip> <skip>Compensation</skip> <skip>Law</skip> <skip>of</skip> <skip>the</skip> <skip>State</skip> <skip>of</skip> <skip>Louisiana</skip> <skip>and</skip> <skip>further</skip> <skip>under</skip> <skip>the</skip> <skip>provisions</skip> <skip>of</skip> <skip>R</skip> <skip>S</skip> <skip>23</skip> <skip>1034</skip> <skip>anyone</skip> <skip>employed</skip> <skip>by</skip> <skip>the</skip> <skip>Contractor</skip> <skip>shall</skip> <skip>not</skip> <skip>be</skip> <skip>considered</skip> <skip>an</skip> <skip>employee</skip> <skip>of</skip> <skip>the</skip> <skip>City</skip> <skip>for</skip> <skip>the</skip> <skip>purpose</skip> <skip>of</skip> <skip>Worker</skip> <skip>s</skip> <skip>Compensation</skip> <skip>coverage</skip> <skip>6</skip> <skip>ACKNOWLEDGMENT</skip> <skip>OF</skip> <skip>EXCLUSION</skip> <skip>OF</skip> <skip>UNEMPLOYMENT</skip> <skip>COMPENSATION</skip> <skip>COVERAGE</skip> <skip>Contractor</skip> <skip>herein</skip> <skip>expressly</skip> <skip>declares</skip> <skip>and</skip> <skip>acknowledges</skip> <skip>that</skip> <skip>it</skip> <skip>is</skip> <skip>an</skip> <skip>independent</skip> <skip>contractor</skip> <skip>and</skip> <skip>as</skip> <skip>such</skip> <skip>is</skip> <skip>being</skip> <skip>hired</skip> <skip>by</skip> <skip>the</skip> <skip>City</skip> <skip>under</skip> <skip>this</skip> <skip>agreement</skip> <skip>for</skip> <skip>hire</skip> <skip>as</skip> <skip>noted</skip> <skip>and</skip> <skip>defined</skip> <skip>in</skip> <skip>R</skip> <skip>S</skip> <skip>23</skip> <skip>1472</skip> <skip>E</skip> <skip>and</skip> <skip>therefore</skip> <skip>it</skip> <skip>is</skip> <skip>expressly</skip> <skip>declared</skip> <skip>and</skip> <skip>understood</skip> <skip>between</skip> <skip>the</skip> <skip>parties</skip> <skip>hereto</skip> <skip>in</skip> <skip>entering</skip> <skip>into</skip> <skip>this</skip> <skip>services</skip> <skip>agreement</skip> <skip>or</skip> <skip>agreement</skip> <skip>for</skip> <skip>hire</skip> <skip>and</skip> <skip>in</skip> <skip>connection</skip> <skip>with</skip> <skip>unemployment</skip> <skip>compensation</skip> <skip>only</skip> <skip>that</skip> <skip>a</skip> <skip>Contractor</skip> <skip>has</skip> <skip>been</skip> <skip>and</skip> <skip>will</skip> <skip>be</skip> <skip>free</skip> <skip>from</skip> <skip>any</skip> <skip>control</skip> <skip>or</skip> <skip>direction</skip> <skip>by</skip> <skip>the</skip> <skip>City</skip> <skip>over</skip> <skip>the</skip> <skip>performance</skip> <skip>of</skip> <skip>the</skip> <skip>services</skip> <skip>covered</skip> <skip>by</skip> <skip>this</skip> <skip>contract</skip> <skip>and</skip> <skip>b</skip> <skip>Services</skip> <skip>to</skip> <skip>be</skip> <skip>performed</skip> <skip>by</skip> <skip>Contractor</skip> <skip>are</skip> <skip>outside</skip> <skip>the</skip> <skip>normal</skip> <skip>course</skip> <skip>and</skip> <skip>scope</skip> <skip>of</skip> <skip>the</skip> <skip>City</skip> <skip>s</skip> <skip>usual</skip> <skip>business</skip> <skip>and</skip> <skip>c</skip> <skip>Contractor</skip> <skip>has</skip> <skip>been</skip> <skip>independently</skip> <skip>engaged</skip> <skip>in</skip> <skip>performing</skip> <skip>the</skip> <skip>services</skip> <skip>listed</skip> <skip>herein</skip> <skip>prior</skip> <skip>to</skip> <skip>the</skip> <skip>date</skip> <skip>of</skip> <skip>this</skip> <skip>agreement</skip> <skip>Consequently</skip> <skip>neither</skip> <skip>Contractor</skip> <skip>nor</skip> <skip>anyone</skip> <skip>employed</skip> <skip>by</skip> <skip>Contractor</skip> <skip>shall</skip> <skip>be</skip> <skip>considered</skip> <skip>an</skip> <skip>employee</skip> <skip>of</skip> <skip>the</skip> <skip>City</skip> <skip>for</skip> <skip>the</skip> <skip>purpose</skip> <skip>of</skip> <skip>unemployment</skip> <skip>compensation</skip> <skip>coverage</skip> <skip>the</skip> <skip>same</skip> <skip>being</skip> <skip>hereby</skip> <skip>expressly</skip> <skip>waived</skip> <skip>and</skip> <skip>excluded</skip> <skip>by</skip> <skip>the</skip> <skip>parties</skip> <skip>hereto</skip> <skip>WAIVER</skip> <skip>OF</skip> <skip>SICK</skip> <skip>AND</skip> <skip>ANNUAL</skip> <skip>LEAVE</skip> <skip>BENEFITS</skip> <skip>It</skip> <skip>is</skip> <skip>expressly</skip> <skip>agreed</skip> <skip>and</skip> <skip>understood</skip> <skip>7</skip> <skip>between</skip> <skip>the</skip> <skip>parties</skip> <skip>entering</skip> <skip>into</skip> <skip>this</skip> <skip>services</skip> <skip>agreement</skip> <skip>that</skip> <skip>the</skip> <skip>Contractor</skip> <skip>acting</skip> <skip>as</skip> <skip>an</skip> <skip>independent</skip> <skip>agent</skip> <skip>shall</skip> <skip>not</skip> <skip>receive</skip> <skip>any</skip> <skip>sick</skip> <skip>and</skip> <skip>annual</skip> <skip>leave</skip> <skip>benefits</skip> <skip>from</skip> <skip>the</skip> <skip>City</skip> <skip>of</skip> <skip>New</skip> <skip>Orleans</skip> <skip>JURISDICTION</skip> <skip>The</skip> <skip>Contractor</skip> <skip>hereby</skip> <skip>consents</skip> <skip>and</skip> <skip>yields</skip> <skip>to</skip> <skip>the</skip> <skip>jurisdiction</skip> <skip>of</skip> <skip>the</skip> <skip>State</skip> <skip>Civil</skip> <skip>8</skip> <skip>Courts</skip> <skip>of</skip> <skip>the</skip> <skip>Parish</skip> <skip>of</skip> <skip>Orleans</skip> <skip>and</skip> <skip>does</skip> <skip>hereby</skip> <skip>formally</skip> <skip>waive</skip> <skip>any</skip> <skip>pleas</skip> <skip>of</skip> <skip>jurisdiction</skip> <skip>on</skip> <skip>account</skip> <skip>of</skip> <skip>the</skip> <skip>residence</skip> <skip>elsewhere</skip> <skip>of</skip> <skip>the</skip> <skip>Contractor</skip> <skip>DURATION</skip> <skip>The</skip> <skip>services</skip> <skip>to</skip> <skip>be</skip> <skip>provided</skip> <skip>under</skip> <skip>the</skip> <skip>terms</skip> <skip>of</skip> <skip>this</skip> <skip>agreement</skip> <skip>shall</skip> <skip>begin</skip> <skip>on</skip> <skip>9</skip> <skip>START</skip> <skip>and</skip> <skip>shall</skip> <skip>end</skip> <skip>no</skip> <skip>later</skip> <skip>than</skip> <skip>END</skip> <skip>It</skip> <skip>is</skip> <skip>understood</skip> <skip>and</skip> <skip>acknowledged</skip> <skip>by</skip> <skip>all</skip> <skip>signers</skip> <skip>to</skip> <skip>this</skip> <skip>Agreement</skip> <skip>that</skip> <skip>work</skip> <skip>described</skip> <skip>under</skip> <skip>these</skip> <skip>terms</skip> <skip>is</skip> <skip>to</skip> <skip>be</skip> <skip>accomplished</skip> <skip>during</skip> <skip>the</skip> <skip>time</skip> <skip>period</skip> <skip>specified</skip> <skip>herein</skip> <skip>The</skip> <skip>terms</skip> <skip>conditions</skip> <skip>and</skip> <skip>duration</skip> <skip>of</skip> <skip>this</skip> <skip>agreement</skip> <skip>may</skip> <skip>be</skip> <skip>modified</skip> <skip>by</skip> <skip>an</skip> <skip>executed</skip> <skip>written</skip> <skip>amendment</skip> <skip>to</skip> <skip>this</skip> <skip>Agreement</skip> <skip>EXTENSION</skip> <skip>This</skip> <skip>agreement</skip> <skip>may</skip> <skip>be</skip> <skip>extended</skip> <skip>at</skip> <skip>the</skip> <skip>option</skip> <skip>of</skip> <skip>the</skip> <skip>City</skip> <skip>provided</skip> <skip>that</skip> <skip>funds</skip> <skip>are</skip> <skip>10</skip> <skip>allocated</skip> <skip>by</skip> <skip>the</skip> <skip>Council</skip> <skip>of</skip> <skip>the</skip> <skip>City</skip> <skip>of</skip> <skip>New</skip> <skip>Orleans</skip> <skip>and</skip> <skip>the</skip> <skip>extension</skip> <skip>of</skip> <skip>the</skip> <skip>agreement</skip> <skip>facilitates</skip> <skip>the</skip> <skip>continuity</skip> <skip>of</skip> <skip>services</skip> <skip>provided</skip> <skip>herein</skip> <skip>This</skip> <skip>agreement</skip> <skip>may</skip> <skip>be</skip> <skip>extended</skip> <skip>by</skip> <skip>the</skip> <skip>City</skip> <skip>on</skip> <skip>an</skip> <skip>annual</skip> <skip>basis</skip> <skip>for</skip> <skip>no</skip> <skip>longer</skip> <skip>than</skip> <skip>five</skip> <skip>one</skip> <skip>year</skip> <skip>periods</skip> <skip>CANCELLATION</skip> <skip>Either</skip> <skip>party</skip> <skip>to</skip> <skip>this</skip> <skip>contract</skip> <skip>may</skip> <skip>terminate</skip> <skip>the</skip> <skip>agreement</skip> <skip>at</skip> <skip>any</skip> <skip>time</skip> <skip>during</skip> <skip>the</skip> <skip>11</skip> <skip>term</skip> <skip>of</skip> <skip>the</skip> <skip>agreement</skip> <skip>by</skip> <skip>giving</skip> <skip>the</skip> <skip>other</skip> <skip>party</skip> <skip>written</skip> <skip>notice</skip> <skip>of</skip> <skip>said</skip> <skip>intention</skip> <skip>to</skip> <skip>terminate</skip> <skip>at</skip> <skip>least</skip> <skip>30</skip> <skip>days</skip> <skip>before</skip> <skip>the</skip> <skip>date</skip> <skip>of</skip> <skip>termination</skip> <skip>SOLICITATION</skip> <skip>The</skip> <skip>Contractor</skip> <skip>has</skip> <skip>not</skip> <skip>employed</skip> <skip>or</skip> <skip>retained</skip> <skip>any</skip> <skip>company</skip> <skip>or</skip> <skip>person</skip> <skip>other</skip> <skip>than</skip> <skip>a</skip> <skip>12</skip> <skip>bona</skip> <skip>fide</skip> <skip>employee</skip> <skip>working</skip> <skip>solely</skip> <skip>for</skip> <skip>him</skip> <skip>to</skip> <skip>solicit</skip> <skip>or</skip> <skip>secure</skip> <skip>the</skip> <skip>subject</skip> <skip>contract</skip> <skip>The</skip> <skip>Contractor</skip> <skip>has</skip> <skip>not</skip> <skip>paid</skip> <skip>or</skip> <skip>agreed</skip> <skip>to</skip> <skip>pay</skip> <skip>any</skip> <skip>person</skip> <skip>other</skip> <skip>than</skip> <skip>a</skip> <skip>bona</skip> <skip>fide</skip> <skip>employee</skip> <skip>working</skip> <skip>for</skip> <skip>him</skip> <skip>any</skip> <skip>fee</skip> <skip>commission</skip> <skip>percentage</skip> <skip>gift</skip> <skip>or</skip> <skip>any</skip> <skip>other</skip> <skip>consideration</skip> <skip>contingent</skip> <skip>upon</skip> <skip>or</skip> <skip>resulting</skip> <skip>from</skip> <skip>the</skip> <skip>subject</skip> <skip>contract</skip> <skip>AUDIT</skip> <skip>AND</skip> <skip>OTHER</skip> <skip>OVERSIGHT</skip> <skip>The</skip> <skip>Contractor</skip> <skip>understands</skip> <skip>and</skip> <skip>will</skip> <skip>abide</skip> <skip>by</skip> <skip>all</skip> <skip>provisions</skip> <skip>of</skip> <skip>13</skip> <skip>the</skip> <skip>Code</skip> <skip>of</skip> <skip>the</skip> <skip>City</skip> <skip>of</skip> <skip>New</skip> <skip>Orleans</skip> <skip>Chapter</skip> <skip>2</skip> <skip>Art</skip> <skip>XIII</skip> <skip>Sect</skip> <skip>2</skip> <skip>1120</skip> <skip>as</skip> <skip>adopted</skip> <skip>by</skip> <skip>City</skip> <skip>Ordinance</skip> <skip>No</skip> <skip>22</skip> <skip>888</skip> <skip>M</skip> <skip>C</skip> <skip>S</skip> <skip>relative</skip> <skip>to</skip> <skip>the</skip> <skip>operations</skip> <skip>and</skip> <skip>authority</skip> <skip>of</skip> <skip>the</skip> <skip>City</skip> <skip>Inspector</skip> <skip>General</skip> <skip>incorporated</skip> <skip>herein</skip> <skip>by</skip> <skip>reference</skip></amount_string>
</Collection>
